atproto/__init__.py
atproto/exceptions.py
atproto_cli/__init__.py
atproto_cli/cli.py
atproto_client/__init__.py
atproto_client/client/__init__.py
atproto_client/client/async_client.py
atproto_client/client/async_raw.py
atproto_client/client/base.py
atproto_client/client/client.py
atproto_client/client/methods_mixin/__init__.py
atproto_client/client/methods_mixin/headers.py
atproto_client/client/methods_mixin/session.py
atproto_client/client/methods_mixin/time.py
atproto_client/client/raw.py
atproto_client/client/session.py
atproto_client/exceptions.py
atproto_client/models/__init__.py
atproto_client/models/app/__init__.py
atproto_client/models/app/bsky/__init__.py
atproto_client/models/app/bsky/actor/__init__.py
atproto_client/models/app/bsky/actor/defs.py
atproto_client/models/app/bsky/actor/get_preferences.py
atproto_client/models/app/bsky/actor/get_profile.py
atproto_client/models/app/bsky/actor/get_profiles.py
atproto_client/models/app/bsky/actor/get_suggestions.py
atproto_client/models/app/bsky/actor/profile.py
atproto_client/models/app/bsky/actor/put_preferences.py
atproto_client/models/app/bsky/actor/search_actors.py
atproto_client/models/app/bsky/actor/search_actors_typeahead.py
atproto_client/models/app/bsky/embed/__init__.py
atproto_client/models/app/bsky/embed/defs.py
atproto_client/models/app/bsky/embed/external.py
atproto_client/models/app/bsky/embed/images.py
atproto_client/models/app/bsky/embed/record.py
atproto_client/models/app/bsky/embed/record_with_media.py
atproto_client/models/app/bsky/embed/video.py
atproto_client/models/app/bsky/feed/__init__.py
atproto_client/models/app/bsky/feed/defs.py
atproto_client/models/app/bsky/feed/describe_feed_generator.py
atproto_client/models/app/bsky/feed/generator.py
atproto_client/models/app/bsky/feed/get_actor_feeds.py
atproto_client/models/app/bsky/feed/get_actor_likes.py
atproto_client/models/app/bsky/feed/get_author_feed.py
atproto_client/models/app/bsky/feed/get_feed.py
atproto-0.0.60.dist-info/LICENSE
atproto-0.0.60.dist-info/METADATA
atproto-0.0.60.dist-info/WHEEL
atproto-0.0.60.dist-info/entry_points.txt
atproto-0.0.60.dist-info/RECORD
