Metadata-Version: 2.1
Name: atproto
Version: 0.0.60
Summary: The AT Protocol SDK
Home-page: https://github.com/MarshalX/atproto
License: MIT
Keywords: library,sdk,codegen,xrpc,xrpc-client,atprotocol,atproto,lexicon,parser,schema,bluesky,bluesky-api,at,uri,atp,nsid,did,cid
Author: Ilya (Marshal)
Author-email: ilya@marshal.dev
Requires-Python: >=3.8,<3.14
Classifier: Development Status :: 3 - Alpha
Classifier: Intended Audience :: Developers
Classifier: License :: OSI Approved :: MIT License
Classifier: Natural Language :: English
Classifier: Operating System :: OS Independent
Classifier: Programming Language :: Python
Classifier: Programming Language :: Python :: 3
Classifier: Programming Language :: Python :: 3.8
Classifier: Programming Language :: Python :: 3.9
Classifier: Programming Language :: Python :: 3.10
Classifier: Programming Language :: Python :: 3.11
Classifier: Programming Language :: Python :: 3.12
Classifier: Programming Language :: Python :: 3 :: Only
Classifier: Programming Language :: Python :: 3.13
Classifier: Topic :: Software Development
Classifier: Topic :: Software Development :: Libraries :: Python Modules
Classifier: Topic :: Software Development :: Pre-processors
Requires-Dist: click (>=8.1.3,<9)
Requires-Dist: cryptography (>=41.0.7,<46)
Requires-Dist: dnspython (>=2.4.0,<3)
Requires-Dist: httpx (>=0.25.0,<0.29.0)
Requires-Dist: libipld (>=3.0.1,<4)
Requires-Dist: pydantic (>=2.7,<3)
Requires-Dist: typing-extensions (>=4.8.0,<5)
Requires-Dist: websockets (>=12,<14)
Project-URL: Author, https://github.com/MarshalX
Project-URL: Changes, https://github.com/MarshalX/atproto/blob/main/CHANGES.md
Project-URL: Documentation, https://atproto.blue
Project-URL: Repository, https://github.com/MarshalX/atproto
Project-URL: Tracker, https://github.com/MarshalX/atproto/issues
